timing_models/a3.v
module comb_delay(in_a, in_b, in_c, out);

	input	in_a, in_b, in_c;
	output	out;
	wire	fan_1, fan_2, fan_3, fan_4, fan_5;
	
	and	#(2:2:3) gat1 (fan_1, in_a, in_b);
	or	#(1:2:3) gat2 (fan_2, in_b, in_c);
	nand	#(2:2:3) gat3 (fan_3, fan_1, fan_2);
	nor	#(1:2:3) gat4 (fan_4, fan_1, in_a);
	or	#(1:2:3) gat5 (fan_5, fan_3, in_c);
	and	#(2:2:3) gat6 (out, fan_4, fan_5);

endmodule

timing_models/a_tb.v
module a_tb;
	
	reg	in_a, in_b, in_c;
	wire	out;
	comb_delay dut (in_a, in_b, in_c, out);

	initial begin
		$dumpfile("a.vcd");
		$dumpvars(0, a_tb);
	end

	initial repeat(100) begin
		#10;
		in_a = {$random} % 2;
		in_b = {$random} % 2;
		in_c = {$random} % 2;
	end
	
endmodule

timing_models/a.vcd
$date
	Fri Sep 10 20:53:23 2021
$end
$version
	Icarus Verilog
$end
$timescale
	1s
$end
$scope module a_tb $end
$var wire 1 ! out $end
$var reg 1 " in_a $end
$var reg 1 # in_b $end
$var reg 1 $ in_c $end
$scope module dut $end
$var wire 1 % fan_1 $end
$var wire 1 & fan_2 $end
$var wire 1 ' fan_3 $end
$var wire 1 ( fan_4 $end
$var wire 1 ) fan_5 $end
$var wire 1 " in_a $end
$var wire 1 # in_b $end
$var wire 1 $ in_c $end
$var wire 1 ! out $end
$upscope $end
$upscope $end
$enddefinitions $end
#0
$dumpvars
x)
x(
x'
x&
x%
x$
x#
x"
x!
$end
#10
1$
1#
0"
#14
1)
1&
0%
#17
1'
1(
#20
1"
#21
1!
#23
0(
#24
1%
#27
0'
0!
#30
0#
#34
0%
#37
1'
#60
0$
1#
0"
#63
1(
#67
1!
#70
1"
#73
0(
#74
1%
#77
0'
0!
#80
0#
#81
0)
#84
0%
0&
#87
1'
#90
1#
0"
#91
1)
#93
1(
#94
1&
#97
1!
#100
1$
1"
#103
0(
#104
1%
#107
0'
0!
#110
0$
0#
#114
0)
0%
0&
#117
1'
#120
1$
0"
#121
1)
#123
1(
#124
1&
#127
1!
#130
1#
#140
1"
#143
0(
#144
1%
#147
0'
0!
#150
0#
0"
#154
0%
#157
1'
1(
#160
0$
1#
1"
#161
1!
#163
0(
#164
1%
#167
0'
0!
#170
0#
0"
#171
0)
#174
0&
0%
#177
1'
1(
#180
1#
#181
1)
#184
1&
#185
1!
#190
1$
#200
0$
0#
#204
0&
#210
1$
#214
1&
#220
1#
1"
#223
0(
#224
1%
#227
0'
0!
#230
0$
0#
#234
0)
0%
0&
#237
1'
#240
1$
1#
#241
1)
#244
1%
1&
#247
0'
#250
0#
0"
#254
0%
#257
1'
1(
#260
1"
#261
1!
#263
0(
#267
0!
#280
0$
1#
#284
1%
#287
0'
#291
0)
#300
0#
0"
#304
0&
0%
#307
1'
1(
#310
1#
1"
#311
1)
#313
0(
#314
1&
1%
#317
0'
#320
1$
0"
#324
0%
#327
1'
1(
#330
1"
#331
1!
#333
0(
#334
1%
#337
0'
0!
#340
0"
#344
0%
#347
1'
1(
#350
0$
0#
1"
#351
1!
#353
0(
#354
0&
#357
0!
#360
0"
#363
1(
#367
1!
#370
1$
#374
1&
#380
1#
1"
#383
0(
#384
1%
#387
0'
0!
#390
0#
#394
0%
#397
1'
#400
0$
#404
0&
#410
1#
#414
1%
1&
#417
0'
#420
1$
#430
0$
0#
#434
0)
0%
0&
#437
1'
#440
1#
0"
#441
1)
#443
1(
#444
1&
#447
1!
#450
1$
0#
#460
0$
1"
#463
0(
#464
0&
#467
0!
#480
1#
0"
#483
1(
#484
1&
#487
1!
#500
1$
1"
#503
0(
#504
1%
#507
0'
0!
#510
0$
#514
0)
#520
1$
0#
0"
#524
1)
0%
#527
1'
1(
#531
1!
#540
0$
1"
#543
0(
#544
0&
#547
0!
#550
1$
1#
0"
#553
1(
#554
1&
#557
1!
#560
0$
0#
#564
0&
#570
1#
1"
#573
0(
#574
1&
1%
#577
0'
0!
#580
1$
0#
0"
#584
0%
#587
1'
1(
#591
1!
#600
0$
#604
0&
#610
1$
1"
#613
0(
#614
1&
#617
0!
#620
0$
#624
0&
#630
1$
0"
#633
1(
#634
1&
#637
1!
#640
0$
#644
0&
#650
1$
1#
#654
1&
#660
0#
1"
#663
0(
#667
0!
#670
0$
1#
#674
1%
#677
0'
#680
1$
0"
#684
0%
#687
1'
1(
#690
1"
#691
1!
#693
0(
#694
1%
#697
0'
0!
#700
0"
#704
0%
#707
1'
1(
#710
0$
0#
#711
1!
#714
0&
#720
1$
1#
#724
1&
#730
0#
#770
0$
1#
1"
#773
0(
#774
1%
#777
0'
0!
#780
1$
0#
0"
#784
0%
#787
1'
1(
#791
1!
#800
0$
#804
0&
#810
1#
#814
1&
#820
1$
0#
#830
1"
#833
0(
#837
0!
#840
1#
#844
1%
#847
0'
#850
0"
#854
0%
#857
1'
1(
#860
0$
0#
1"
#861
1!
#863
0(
#864
0&
#867
0!
#880
1#
#884
1%
1&
#887
0'
#890
0"
#891
0)
#894
0%
#897
1'
1(
#901
1)
#905
1!
#910
1"
#913
0(
#914
1%
#917
0'
0!
#920
1$
0#
#924
0%
#927
1'
#930
0"
#933
1(
#937
1!
#940
0$
#944
0&
#950
1$
1#
1"
#953
0(
#954
1&
1%
#957
0'
0!
#960
0$
#964
0)
#970
1$
#974
1)
#980
0$
0#
0"
#984
0)
0&
0%
#987
1'
1(
#991
1)
#995
1!
#1000
1$
1#
1"
#1003
0(
#1004
1&
1%
#1007
0'
0!
